README.md
setup.py
outband/__init__.py
outband/__main__.py
outband/base_connector.py
outband/java_security.py
outband/util.py
outband.egg-info/PKG-INFO
outband.egg-info/SOURCES.txt
outband.egg-info/dependency_links.txt
outband.egg-info/entry_points.txt
outband.egg-info/requires.txt
outband.egg-info/top_level.txt
outband/connectors/__init__.py
outband/connectors/auto.py
outband/connectors/drac6.py