Metadata-Version: 2.1
Name: outband
Version: 1.0.0
Summary: Connect to an out-of-band management KVM console from the command line.
Home-page: https://github.com/chrisgavin/outband/
License: UNKNOWN
Platform: UNKNOWN
Classifier: Programming Language :: Python :: 3
Classifier: Programming Language :: Python :: 3.5
Classifier: Programming Language :: Python :: 3.6
Classifier: Programming Language :: Python :: 3 :: Only
Requires-Python: >=3.5
Provides-Extra: dev
